mph/__init__.py
mph/client.py
mph/config.py
mph/discovery.py
mph/meta.py
mph/model.py
mph/node.py
mph/py.typed
mph/server.py
mph/session.py
mph/tags.json
mph-1.3.1.dist-info/licenses/license.txt
mph-1.3.1.dist-info/WHEEL
mph-1.3.1.dist-info/METADATA
mph-1.3.1.dist-info/RECORD
