Metadata-Version: 2.4
Name: MPh
Version: 1.3.1
Summary: Pythonic scripting interface for Comsol Multiphysics
Keywords: Comsol,multiphysics,physics,finite elements,computer simulation
Author: John Hennig
License-Expression: MIT
License-File: license.txt
Classifier: Development Status :: 5 - Production/Stable
Classifier: Topic :: Scientific/Engineering :: Physics
Classifier: Intended Audience :: Science/Research
Requires-Dist: jpype1
Requires-Dist: numpy
Requires-Python: >=3.10
Project-URL: Documentation, https://mph.readthedocs.io
Project-URL: Source, https://github.com/MPh-py/MPh
